fastdfs_client/__init__.py
fastdfs_client/client.py
fastdfs_client/connection.py
fastdfs_client/exceptions.py
fastdfs_client/protols.py
fastdfs_client/py.typed
fastdfs_client/storage_client.py
fastdfs_client/tracker_client.py
fastdfs_client/utils.py
fastdfs_client-1.2.3.dist-info/LICENSE
fastdfs_client-1.2.3.dist-info/METADATA
fastdfs_client-1.2.3.dist-info/WHEEL
fastdfs_client-1.2.3.dist-info/RECORD
