Metadata-Version: 2.3
Name: fastdfs-client
Version: 1.2.3
Summary: Python Implement for FastDFS Client
Author: Waket Zheng
Author-email: waketzheng@gmail.com
Requires-Python: >=3.9
Classifier: Programming Language :: Python :: 3
Classifier: Programming Language :: Python :: 3.9
Classifier: Programming Language :: Python :: 3.10
Classifier: Programming Language :: Python :: 3.11
Classifier: Programming Language :: Python :: 3.12
Classifier: Programming Language :: Python :: 3.13
Provides-Extra: aio
Requires-Dist: anyio (>=4.0.0,<5.0.0) ; extra == "aio"
